deadline/cinema4d_adaptor/__init__.py
deadline/cinema4d_adaptor/_version.py
deadline/cinema4d_adaptor/Cinema4DAdaptor/Cinema4DAdaptor.json
deadline/cinema4d_adaptor/Cinema4DAdaptor/__init__.py
deadline/cinema4d_adaptor/Cinema4DAdaptor/__main__.py
deadline/cinema4d_adaptor/Cinema4DAdaptor/adaptor.py
deadline/cinema4d_adaptor/Cinema4DAdaptor/adaptor.sh
deadline/cinema4d_adaptor/Cinema4DAdaptor/schemas/init_data.schema.json
deadline/cinema4d_adaptor/Cinema4DAdaptor/schemas/run_data.schema.json
deadline/cinema4d_adaptor/Cinema4DClient/__init__.py
deadline/cinema4d_adaptor/Cinema4DClient/cinema4d_client.py
deadline/cinema4d_adaptor/Cinema4DClient/cinema4d_handler.py
deadline/cinema4d_adaptor/Cinema4DClient/plugin/DeadlineCloudClient.pyp
deadline/cinema4d_submitter/__init__.py
deadline/cinema4d_submitter/_version.py
deadline/cinema4d_submitter/adaptor_cinema4d_job_template.yaml
deadline/cinema4d_submitter/adaptor_override_environment.yaml
deadline/cinema4d_submitter/assets.py
deadline/cinema4d_submitter/cinema4d_render_submitter.py
deadline/cinema4d_submitter/data_classes.py
deadline/cinema4d_submitter/default_cinema4d_job_template.yaml
deadline/cinema4d_submitter/detailed_logging_utils.py
deadline/cinema4d_submitter/enums.py
deadline/cinema4d_submitter/font_installer.py
deadline/cinema4d_submitter/font_utils.py
deadline/cinema4d_submitter/integ_test_helpers.py
deadline/cinema4d_submitter/path_validator.py
deadline/cinema4d_submitter/platform_utils.py
deadline/cinema4d_submitter/scene.py
deadline/cinema4d_submitter/style.py
deadline/cinema4d_submitter/takes.py
deadline/cinema4d_submitter/template_timeout_patcher.py
deadline/cinema4d_submitter/warning_collector.py
deadline/cinema4d_submitter/warning_logging_handler.py
deadline/cinema4d_submitter/detailed_logging_scripts/__init__.py
deadline/cinema4d_submitter/detailed_logging_scripts/print_logs.py
deadline/cinema4d_submitter/detailed_logging_scripts/setup_logging.py
deadline/cinema4d_submitter/ui/__init__.py
deadline_cloud_for_cinema_4d-0.9.2.dist-info/METADATA
deadline_cloud_for_cinema_4d-0.9.2.dist-info/WHEEL
deadline_cloud_for_cinema_4d-0.9.2.dist-info/entry_points.txt
deadline_cloud_for_cinema_4d-0.9.2.dist-info/licenses/LICENSE
deadline_cloud_for_cinema_4d-0.9.2.dist-info/licenses/NOTICE
deadline_cloud_for_cinema_4d-0.9.2.dist-info/RECORD
