Metadata-Version: 2.4
Name: deadline-cloud-for-cinema-4d
Version: 0.9.2
Summary: AWS Deadline Cloud for Cinema 4D
Project-URL: Homepage, https://github.com/aws-deadline/deadline-cloud-for-cinema-4d
Project-URL: Source, https://github.com/aws-deadline/deadline-cloud-for-cinema-4d
Author: Amazon Web Services
License-Expression: Apache-2.0
License-File: LICENSE
License-File: NOTICE
Classifier: Development Status :: 5 - Production/Stable
Classifier: Intended Audience :: Developers
Classifier: Intended Audience :: End Users/Desktop
Classifier: License :: OSI Approved :: Apache Software License
Classifier: Operating System :: MacOS
Classifier: Operating System :: Microsoft :: Windows
Classifier: Operating System :: POSIX :: Linux
Classifier: Programming Language :: Python
Classifier: Programming Language :: Python :: 3 :: Only
Classifier: Programming Language :: Python :: 3.9
Classifier: Programming Language :: Python :: 3.10
Classifier: Programming Language :: Python :: 3.11
Classifier: Programming Language :: Python :: 3.12
Requires-Python: >=3.9
Requires-Dist: deadline<0.55,>=0.51.1
Requires-Dist: fonttools<4.61,>=4.59.2; sys_platform == 'win32'
Requires-Dist: openjd-adaptor-runtime<0.10,>=0.7
